ovc/__init__.py
ovc/client.py
ovc/cloudspace.py
ovc/disk.py
ovc/machine.py
ovc/portforwarding.py
ovc-0.1.3.dist-info/DESCRIPTION.rst
ovc-0.1.3.dist-info/METADATA
ovc-0.1.3.dist-info/RECORD
ovc-0.1.3.dist-info/WHEEL
ovc-0.1.3.dist-info/metadata.json
ovc-0.1.3.dist-info/top_level.txt
