Metadata-Version: 2.0
Name: ovc
Version: 0.1.3
Summary: SDK for ansible modules used by GiG for their OpenVCloud platform
Home-page: UNKNOWN
Author: Stef Graces
Author-email: UNKNOWN
License: Nubera BVBA
Platform: UNKNOWN
Classifier: Operating System :: OS Independent
